Metadata-Version: 2.1
Name: pdfsim
Version: 0.2
Summary: A CLI tool to find similar PDF.
Home-page: https://github.com/yourusername/invoice_similarity
Author: Krishav Raj Singh
Author-email: krishavrajsingh@example.com
License: UNKNOWN
Platform: UNKNOWN
Classifier: Programming Language :: Python :: 3
Classifier: License :: OSI Approved :: MIT License
Classifier: Operating System :: OS Independent
Requires-Python: >=3.6
